src/main.py
src/foodpkg/__init__.py
src/foodpkg/add_food_db.py
src/foodpkg/food_helper.py
src/foodpkg/last_month.py
src/foodpkg/pie_chart.py
src/foodpkg/run.py
food_app-0.1.5.dist-info/METADATA
food_app-0.1.5.dist-info/WHEEL
food_app-0.1.5.dist-info/entry_points.txt
food_app-0.1.5.dist-info/top_level.txt
food_app-0.1.5.dist-info/RECORD
