Metadata-Version: 2.4
Name: food-app
Version: 0.1.5
Summary: A cli food app to calculate Kcal, Carbs, Protein and Fat.
Project-URL: Repository, https://gitlab.com/eklownr/food_app.git
Requires-Python: >=3.13
Requires-Dist: rich
Requires-Dist: matplot
